lucaswangtool/__init__.py
lucaswangtool/core.py
lucaswangtool-0.0.1.dist-info/licenses/LICENSE
lucaswangtool-0.0.1.dist-info/METADATA
lucaswangtool-0.0.1.dist-info/WHEEL
lucaswangtool-0.0.1.dist-info/top_level.txt
lucaswangtool-0.0.1.dist-info/RECORD
