Metadata-Version: 2.4
Name: lucaswangtool
Version: 0.0.1
Summary: 一个演示用数学运算库
Home-page: https://github.com/lucaswangdev/lucaswangtool
Author: lucaswangdev
Author-email: lucaswang.dev@gmail.com
Classifier: Programming Language :: Python :: 3
Classifier: License :: OSI Approved :: MIT License
Requires-Python: >=3.6
License-File: LICENSE
Dynamic: license-file
